jpy_flette/__init__.py
jpy_flette/__version__.py
jpy_flette/jpy_flette.py
jpy_flette/theme-flette/.gitignore
jpy_flette/theme-flette/jpy-flette-theme.yaml
jpy_flette/theme-flette/package.json
jpy_flette/theme-flette/template.html.j2
jpy_flette/theme-flette/css/jupyter_primary_styles_slim.scss
jpy_flette/theme-flette/css/pygments-espresso-highlight.scss
jpy_flette/theme-flette/css/style.css
jpy_flette/theme-flette/css/style.css.map
jpy_flette/theme-flette/css/style.scss
jpy_flette/theme-flette/js/toc-highlight.js
jpy_flette-0.1.0.dist-info/METADATA
jpy_flette-0.1.0.dist-info/RECORD
jpy_flette-0.1.0.dist-info/WHEEL
jpy_flette-0.1.0.dist-info/entry_points.txt
jpy_flette-0.1.0.dist-info/top_level.txt
