Metadata-Version: 2.1
Name: jpy-flette
Version: 0.1.0
Summary: Static site generator for jupyter notebooks
Home-page: https://github.com/r4lv/jpy-flette
Author: Ralf Farkas
Author-email: r4lv@peaxels.com
License: MIT
Platform: UNKNOWN
Classifier: License :: OSI Approved :: MIT License
Classifier: Operating System :: OS Independent
Classifier: Programming Language :: Python
Classifier: Programming Language :: Python :: 3
Classifier: Programming Language :: Python :: 3.5
Classifier: Framework :: Jupyter
Classifier: Intended Audience :: Science/Research
Classifier: Topic :: Documentation
Classifier: Environment :: Console
Requires-Python: >=3.5.0
Requires-Dist: nbconvert
Requires-Dist: click
Requires-Dist: jinja2
Requires-Dist: pyquery
Requires-Dist: ipython
Requires-Dist: pyyaml
